funccomp/__init__.py
funccomp/_const.py
funccomp/core/Composite.py
funccomp/core/__init__.py
funccomp/tests/__init__.py
funccomp/tests/test_comp.py
funccomp/tests/test_slots.py
funccomp/tests/test_starpower.py
funccomp-0.3.3.dist-info/licenses/LICENSE.txt
funccomp-0.3.3.dist-info/METADATA
funccomp-0.3.3.dist-info/WHEEL
funccomp-0.3.3.dist-info/top_level.txt
funccomp-0.3.3.dist-info/RECORD
